vue/__init__.py
vue/lexer.py
vue_lexer-0.0.3.dist-info/LICENSE
vue_lexer-0.0.3.dist-info/METADATA
vue_lexer-0.0.3.dist-info/WHEEL
vue_lexer-0.0.3.dist-info/entry_points.txt
vue_lexer-0.0.3.dist-info/top_level.txt
vue_lexer-0.0.3.dist-info/RECORD
