Metadata-Version: 2.1
Name: vue-lexer
Version: 0.0.3
Summary: A Vue lexer for Pygments
Home-page: https://github.com/testdrivenio/vue-lexer
Author: Michael Herman
Author-email: michael@mherman.org
License: MIT License
Keywords: pygments highlight vue
Platform: UNKNOWN
Classifier: Environment :: Plugins
Classifier: Intended Audience :: Developers
Classifier: Programming Language :: Python :: 2
Classifier: Programming Language :: Python :: 3
Requires-Dist: Pygments (>=2.3)
